{
  "id": "0a904de9c7b1467dbd4d56753dbc5f34",
  "title": "OstrichPreview",
  "description": "OstrichPreview",
  "keyImages": [
    {
      "type": "DieselGameBoxLogo",
      "url": "https://cdn1.epicgames.com/413361d2d5db4912ac2dfbcf27a38141/item/EGS_GLUMBERLAND_OOBLETS_IC1_COLOUR-958x279-03d7224e09b4a949a8e4b2e589e172a0.png",
      "md5": "03d7224e09b4a949a8e4b2e589e172a0",
      "width": 958,
      "height": 279,
      "size": 20910,
      "uploadedDate": "2019-08-19T18:24:16.906Z"
    },
    {
      "type": "DieselGameBox",
      "url": "https://cdn1.epicgames.com/413361d2d5db4912ac2dfbcf27a38141/item/EGS_GLUMBERLAND_OOBLETS_L1_noLogo-2560x1440-95e762adeee5d9d533cf2c1cc2b26ea1.jpg",
      "md5": "95e762adeee5d9d533cf2c1cc2b26ea1",
      "width": 2560,
      "height": 1440,
      "size": 243358,
      "uploadedDate": "2019-08-19T18:24:37.294Z"
    }
  ],
  "categories": [
    {
      "path": "public"
    },
    {
      "path": "games"
    },
    {
      "path": "applications"
    }
  ],
  "namespace": "413361d2d5db4912ac2dfbcf27a38141",
  "status": "ACTIVE",
  "creationDate": "2020-04-24T01:19:27.065Z",
  "lastModifiedDate": "2020-04-24T01:23:21.354Z",
  "customAttributes": {
    "CanRunOffline": {
      "type": "STRING",
      "value": "true"
    },
    "FolderName": {
      "type": "STRING",
      "value": "OstrichPreview"
    }
  },
  "entitlementName": "0a904de9c7b1467dbd4d56753dbc5f34",
  "entitlementType": "EXECUTABLE",
  "itemType": "DURABLE",
  "releaseInfo": [
    {
      "id": "5fc24ece9e364bdaa3af557ca46662b7",
      "appId": "9810369040a54b2282e2d3299ac68415",
      "platform": [
        "Windows"
      ],
      "dateAdded": "2019-08-19T00:00:00.000Z"
    }
  ],
  "developer": "Glumberland",
  "developerId": "o-q293du8hx3hhcjbqzrmfz6cz48hk6x",
  "eulaIds": [
    "egstore"
  ],
  "endOfSupport": false,
  "ageGatings": {},
  "unsearchable": false
}