{
  "id": "169841e5c2804a30a3ae378eaa027e66",
  "title": "LisbonGeneralAudience",
  "description": "LisbonGeneralAudience",
  "categories": [
    {
      "path": "audience"
    },
    {
      "path": "public"
    }
  ],
  "namespace": "16fc138ed83846bc90d923fe0d87ad72",
  "status": "ACTIVE",
  "creationDate": "2020-10-01T17:53:10.546Z",
  "lastModifiedDate": "2020-10-01T18:15:35.029Z",
  "customAttributes": {
    "SupportedPlatforms": {
      "type": "STRING",
      "value": "Windows"
    }
  },
  "entitlementName": "169841e5c2804a30a3ae378eaa027e66",
  "entitlementType": "AUDIENCE",
  "itemType": "DURABLE",
  "developer": "Passion Republic Games",
  "developerId": "o-rbx4uqtxzlz5fmxe82f2frtebbz92h",
  "eulaIds": [
    "egstore"
  ],
  "endOfSupport": false,
  "requiresSecureAccount": false,
  "unsearchable": false
}