{
  "id": "22982a1661d740fe82a982913dbad9ad",
  "title": "Influencer Banner - LeBleDArt",
  "description": "Influencer Banner - LeBleDArt",
  "keyImages": [],
  "categories": [
    {
      "path": "bundles"
    }
  ],
  "namespace": "fn",
  "status": "ACTIVE",
  "creationDate": "2017-06-14T20:03:20.755Z",
  "lastModifiedDate": "2017-06-14T22:44:11.546Z",
  "entitlementName": "INFLUENCERBANNER_LeBleDArt",
  "entitlementType": "ENTITLEMENT",
  "itemType": "DURABLE",
  "developer": "Epic Games",
  "developerId": "o-aa83a0a9bc45e98c80c1b1c9d92e9e",
  "eulaIds": [],
  "endOfSupport": false,
  "unsearchable": false
}