{
  "id": "2576dee96bfe49a9aeb9a80c34cb4bff",
  "title": "Early Access Editor Audience",
  "description": "Early Access Editor Audience",
  "keyImages": [
    {
      "type": "ESRB",
      "url": "https://cdn1.epicgames.com/b9def67e597b4be7a16146146a044d02/item/RP_FOR_E-842x404-fce4fa7233ed80170a8e36079d1e1bde.png",
      "md5": "fce4fa7233ed80170a8e36079d1e1bde",
      "width": 842,
      "height": 404,
      "size": 51194,
      "uploadedDate": "2019-07-24T21:07:05.943Z"
    }
  ],
  "categories": [
    {
      "path": "audience"
    },
    {
      "path": "public"
    }
  ],
  "namespace": "b9def67e597b4be7a16146146a044d02",
  "status": "ACTIVE",
  "creationDate": "2020-11-09T14:51:57.662Z",
  "lastModifiedDate": "2020-11-09T14:54:23.734Z",
  "customAttributes": {
    "SupportedPlatforms": {
      "type": "STRING",
      "value": "Windows"
    }
  },
  "entitlementName": "2576dee96bfe49a9aeb9a80c34cb4bff",
  "entitlementType": "AUDIENCE",
  "itemType": "DURABLE",
  "developer": "Piranha Games",
  "developerId": "o-muad9pj32k67stc4ycpgpplwq84sgq",
  "eulaIds": [
    "egstore"
  ],
  "endOfSupport": false,
  "esrbGameRatingValue": "RATING_PENDING",
  "ageGatings": {},
  "unsearchable": false
}