{
  "id": "3274ef4d92d645df86ae3ecc17d6268f",
  "title": "SnapdragonQAAudience",
  "description": "SnapdragonQAAudience",
  "keyImages": [
    {
      "type": "DieselGameBox",
      "url": "https://cdn1.epicgames.com/snapdragon/item/Metro_PrimaryPromo_update-2580x1450-0e5b7a55fb64f2b4ab1a46455a9293e0.jpg",
      "md5": "0e5b7a55fb64f2b4ab1a46455a9293e0",
      "width": 2580,
      "height": 1450,
      "size": 580337,
      "uploadedDate": "2019-02-14T22:37:09.696Z"
    },
    {
      "type": "DieselGameBoxLogo",
      "url": "https://cdn1.epicgames.com/snapdragon/item/MetroExodus_GameLogo_Update-2850x1450-b14f454728dc4a768250d3bd6f6bb05f.png",
      "md5": "b14f454728dc4a768250d3bd6f6bb05f",
      "width": 2850,
      "height": 1450,
      "size": 605487,
      "uploadedDate": "2019-02-14T22:37:18.936Z"
    }
  ],
  "categories": [
    {
      "path": "audience"
    },
    {
      "path": "developer"
    }
  ],
  "namespace": "snapdragon",
  "status": "ACTIVE",
  "creationDate": "2019-01-30T17:55:04.158Z",
  "lastModifiedDate": "2019-05-13T14:43:39.964Z",
  "customAttributes": {
    "SupportedPlatform": {
      "type": "STRING",
      "value": "Windows"
    }
  },
  "entitlementName": "3274ef4d92d645df86ae3ecc17d6268f",
  "entitlementType": "EXECUTABLE",
  "itemType": "DURABLE",
  "releaseInfo": [],
  "developer": "Koch Media",
  "developerId": "o-jskfz28ywm2l56px6h9rlxplaysrtl",
  "eulaIds": [],
  "endOfSupport": false,
  "unsearchable": false
}