{
  "id": "38acfbfd29b444a0870e6efede8ce230",
  "title": "C_DLC4",
  "description": "C_DLC4",
  "keyImages": [],
  "categories": [
    {
      "path": "audience"
    },
    {
      "path": "public"
    }
  ],
  "namespace": "435aaec1220447efbcfeb4f2abeb1027",
  "status": "ACTIVE",
  "creationDate": "2020-08-18T22:15:34.802Z",
  "lastModifiedDate": "2020-08-24T20:29:17.378Z",
  "customAttributes": {},
  "entitlementName": "38acfbfd29b444a0870e6efede8ce230",
  "entitlementType": "EXECUTABLE",
  "itemType": "CONSUMABLE",
  "releaseInfo": [],
  "developer": "Bethesda Softworks LLC",
  "developerId": "o-bthbhn6wd7fzj73v5p4436ucn3k37u",
  "useCount": 1,
  "eulaIds": [
    "egstore"
  ],
  "endOfSupport": false,
  "ageGatings": {},
  "requiresSecureAccount": false,
  "unsearchable": false
}