{
  "id": "485ac991cae2480f9887daefb5c9bd48",
  "title": "3 out of 10, EP 5: \"The Rig Is Up!\"",
  "description": "3 out of 10, EP 5: \"The Rig Is Up!\"",
  "keyImages": [
    {
      "type": "DieselGameBoxTall",
      "url": "https://cdn1.epicgames.com/6a70006d598948bfa6c71ceb334ad635/item/EGS_3outof10EP5TheRigIsUp_TerriblePostureGamesInc_S2-1200x1600-230f1086d959795ef3df6ce69f915cc6.jpg",
      "md5": "230f1086d959795ef3df6ce69f915cc6",
      "width": 1200,
      "height": 1600,
      "size": 481236,
      "uploadedDate": "2020-09-02T20:22:47.604Z"
    },
    {
      "type": "DieselGameBox",
      "url": "https://cdn1.epicgames.com/6a70006d598948bfa6c71ceb334ad635/item/EGS_3outof10EP5TheRigIsUp_TerriblePostureGamesInc_S1-2560x1440-90a716d5080e7d7f9aefd3bd647c3b6d.jpg",
      "md5": "90a716d5080e7d7f9aefd3bd647c3b6d",
      "width": 2560,
      "height": 1440,
      "size": 766217,
      "uploadedDate": "2020-09-02T20:22:57.662Z"
    }
  ],
  "categories": [
    {
      "path": "public"
    },
    {
      "path": "games"
    },
    {
      "path": "applications"
    }
  ],
  "namespace": "6a70006d598948bfa6c71ceb334ad635",
  "status": "ACTIVE",
  "creationDate": "2020-06-23T03:14:58.717Z",
  "lastModifiedDate": "2020-09-03T14:29:07.991Z",
  "customAttributes": {
    "CanRunOffline": {
      "type": "STRING",
      "value": "true"
    },
    "PresenceId": {
      "type": "STRING",
      "value": "6a70006d598948bfa6c71ceb334ad635"
    },
    "MonitorPresence": {
      "type": "STRING",
      "value": "false"
    },
    "UseAccessControl": {
      "type": "STRING",
      "value": "false"
    },
    "RequirementsJson": {
      "type": "STRING",
      "value": "[]"
    },
    "CanSkipKoreanIdVerification": {
      "type": "STRING",
      "value": "true"
    },
    "FolderName": {
      "type": "STRING",
      "value": "threeoutof10Ep5"
    }
  },
  "entitlementName": "485ac991cae2480f9887daefb5c9bd48",
  "entitlementType": "EXECUTABLE",
  "itemType": "DURABLE",
  "releaseInfo": [
    {
      "id": "547b6e72bd2643179c496737059e214e",
      "appId": "69c5351eacc540fd8850e12e90726e59",
      "platform": [
        "Windows"
      ],
      "dateAdded": "2020-06-23T00:00:00.000Z"
    }
  ],
  "developer": "Terrible Posture Games, Inc.",
  "developerId": "o-2yllrrr7vufkhal9nk3cswwgug977c",
  "eulaIds": [
    "egstore"
  ],
  "endOfSupport": false,
  "ageGatings": {},
  "unsearchable": false
}