{
  "id": "4ed2c720b0454c719f16a816c8f2cd10",
  "title": "CatnipStable1DLC2",
  "description": "CatnipStable1DLC2",
  "keyImages": [],
  "categories": [
    {
      "path": "games"
    },
    {
      "path": "applications"
    }
  ],
  "namespace": "catnip",
  "status": "ACTIVE",
  "creationDate": "2020-01-13T18:49:39.292Z",
  "lastModifiedDate": "2020-06-15T20:52:55.764Z",
  "customAttributes": {
    "OwnershipToken": {
      "type": "STRING",
      "value": "true"
    }
  },
  "entitlementName": "4ed2c720b0454c719f16a816c8f2cd10",
  "entitlementType": "EXECUTABLE",
  "itemType": "DURABLE",
  "releaseInfo": [
    {
      "id": "7bfdfb21a2f44cb5860145b1f0e66e2f",
      "appId": "CatnipStable1DLC2",
      "compatibleApps": [],
      "platform": [
        "Windows",
        "Mac"
      ],
      "dateAdded": "2019-12-03T00:00:00.000Z",
      "releaseNote": "",
      "versionTitle": ""
    }
  ],
  "developer": "2K Games, Inc.",
  "developerId": "o-37m6jbj5wcvrcvm4wusv7nazdfvbjk",
  "eulaIds": [
    "egstore"
  ],
  "endOfSupport": false,
  "unsearchable": false
}