{
  "id": "4ee9b5b343354b0f9db175fd17c5a8b1",
  "title": "Beyond Two Souls JA Demo Audience",
  "description": "Beyond Two Souls JA Demo Audience",
  "keyImages": [
    {
      "type": "ESRB",
      "url": "https://cdn1.epicgames.com/lavender/item/RP_FOR_T_M_AO-418x189-95c21e0dd4a1f73eb8f3848ff306e0f9.png",
      "md5": "95c21e0dd4a1f73eb8f3848ff306e0f9",
      "width": 418,
      "height": 189,
      "size": 8289,
      "uploadedDate": "2019-05-28T12:27:22.589Z"
    }
  ],
  "categories": [
    {
      "path": "audience"
    },
    {
      "path": "public"
    }
  ],
  "namespace": "lavender",
  "status": "ACTIVE",
  "creationDate": "2019-05-28T12:27:37.066Z",
  "lastModifiedDate": "2019-10-16T14:26:04.204Z",
  "customAttributes": {
    "SupportedPlatforms": {
      "type": "STRING",
      "value": "Windows"
    }
  },
  "entitlementName": "4ee9b5b343354b0f9db175fd17c5a8b1",
  "entitlementType": "AUDIENCE",
  "itemType": "DURABLE",
  "releaseInfo": [],
  "developer": "Quantic Dream",
  "developerId": "o-m8v47d762atphw94knus7ezawefpcu",
  "eulaIds": [
    "egstore"
  ],
  "endOfSupport": false,
  "esrbGameRatingValue": "RATING_PENDING",
  "unsearchable": false
}