{
  "id": "71a00317a1b641b19fddc42e22733cb7",
  "title": "SnoekPre-PurchaseAudience",
  "description": "SnoekPre-PurchaseAudience",
  "keyImages": [
    {
      "type": "ESRB",
      "url": "https://cdn1.epicgames.com/11eb2ae2943641b498efb54501511b86/item/ESRB_StateofDecay-842x485-90c5c08d5cbc889d2d5177527c8f1311.jpg",
      "md5": "90c5c08d5cbc889d2d5177527c8f1311",
      "width": 842,
      "height": 485,
      "size": 114080,
      "uploadedDate": "2020-03-06T16:42:55.484Z"
    }
  ],
  "categories": [
    {
      "path": "audience"
    },
    {
      "path": "public"
    }
  ],
  "namespace": "11eb2ae2943641b498efb54501511b86",
  "status": "ACTIVE",
  "creationDate": "2020-03-06T16:14:45.585Z",
  "lastModifiedDate": "2020-05-15T01:04:24.373Z",
  "customAttributes": {
    "SupportedPlatforms": {
      "type": "STRING",
      "value": "Windows"
    }
  },
  "entitlementName": "71a00317a1b641b19fddc42e22733cb7",
  "entitlementType": "AUDIENCE",
  "itemType": "DURABLE",
  "developer": "Microsoft",
  "developerId": "o-f3qq8ygts6pglxx529jhgx5bmyj6bf",
  "eulaIds": [
    "egstore"
  ],
  "endOfSupport": false,
  "esrbGameRatingValue": "MATURE",
  "ageGatings": {},
  "selfRefundable": true,
  "unsearchable": false
}