{
  "id": "7456fb036bcb489699646f02155a2e2b",
  "title": "TanagerDevAudience",
  "description": "TanagerDevAudience",
  "categories": [
    {
      "path": "audience"
    },
    {
      "path": "developer"
    }
  ],
  "namespace": "7f1fa336313d48eca0a802170aa8dd8a",
  "status": "ACTIVE",
  "creationDate": "2019-08-15T17:54:14.761Z",
  "lastModifiedDate": "2020-06-13T19:33:59.057Z",
  "customAttributes": {
    "SupportedPlatforms": {
      "type": "STRING",
      "value": "Windows"
    }
  },
  "entitlementName": "7456fb036bcb489699646f02155a2e2b",
  "entitlementType": "AUDIENCE",
  "itemType": "DURABLE",
  "developer": "Epic Dev Test Account",
  "developerId": "o-ufmrk5furrrxgsp5tdngefzt5rxdcn",
  "eulaIds": [
    "egstore"
  ],
  "endOfSupport": false,
  "unsearchable": false
}