{
  "id": "75214dbabe2d463d878cf88bdbfb1067",
  "title": "Phoenix Point Desktop Wallpaper",
  "description": "Phoenix Point Desktop Wallpaper",
  "keyImages": [
    {
      "type": "Thumbnail",
      "url": "https://cdn1.epicgames.com/iris/item/PhoenixPoint_GameIcon_400x400-400x400-3077494a8cfa2a464958203163c65722.png",
      "md5": "3077494a8cfa2a464958203163c65722",
      "width": 400,
      "height": 400,
      "size": 7129,
      "uploadedDate": "2019-03-12T17:22:06.207Z"
    },
    {
      "type": "DieselGameBoxLogo",
      "url": "https://cdn1.epicgames.com/iris/item/PhoenixPoint_GameLogo_White-1920x258-f459d6f60aceae2e47ce0c6ec6d46471.png",
      "md5": "f459d6f60aceae2e47ce0c6ec6d46471",
      "width": 1920,
      "height": 258,
      "size": 99414,
      "uploadedDate": "2019-03-12T17:22:26.642Z"
    },
    {
      "type": "DieselGameBox",
      "url": "https://cdn1.epicgames.com/iris/item/PhoenixPoint_NEWPROMO-2048x1151-a5d45cf0f70a168b0c1f7eae142a3397.jpg",
      "md5": "a5d45cf0f70a168b0c1f7eae142a3397",
      "width": 2048,
      "height": 1151,
      "size": 2147087,
      "uploadedDate": "2019-07-10T17:22:52.186Z"
    }
  ],
  "categories": [
    {
      "path": "games"
    },
    {
      "path": "applications"
    }
  ],
  "namespace": "iris",
  "status": "ACTIVE",
  "creationDate": "2019-11-01T21:43:34.525Z",
  "lastModifiedDate": "2020-12-04T22:49:19.709Z",
  "customAttributes": {
    "CanRunOffline": {
      "type": "STRING",
      "value": "true"
    },
    "FolderName": {
      "type": "STRING",
      "value": "PhoenixPointWallpaper"
    }
  },
  "entitlementName": "75214dbabe2d463d878cf88bdbfb1067",
  "entitlementType": "EXECUTABLE",
  "itemType": "DURABLE",
  "releaseInfo": [
    {
      "id": "61fcf4610ca843cab0bf38e4db75b764",
      "appId": "IrisWallpaper",
      "compatibleApps": [],
      "platform": [
        "Windows",
        "Mac"
      ],
      "dateAdded": "2019-02-15T00:00:00.000Z",
      "releaseNote": "",
      "versionTitle": ""
    }
  ],
  "developer": "Snapshot Games",
  "developerId": "o-dc63tr2khr4scc36nj3htbpmh3gda6",
  "eulaIds": [
    "egstore"
  ],
  "endOfSupport": false,
  "ageGatings": {},
  "unsearchable": false
}