{
  "id": "779cb62d9b0d472e970115e6b22a03e9",
  "title": "PepperQA",
  "description": "PepperQA",
  "keyImages": [],
  "categories": [
    {
      "path": "games"
    },
    {
      "path": "applications"
    }
  ],
  "namespace": "5d582c08e31a43128a61093a2c3ff7f0",
  "status": "ACTIVE",
  "creationDate": "2019-10-18T16:18:37.683Z",
  "lastModifiedDate": "2019-11-19T12:56:23.766Z",
  "customAttributes": {
    "CanRunOffline": {
      "type": "STRING",
      "value": "true"
    },
    "CanSkipKoreanIdVerification": {
      "type": "STRING",
      "value": "true"
    },
    "FolderName": {
      "type": "STRING",
      "value": "PepperQA"
    }
  },
  "entitlementName": "779cb62d9b0d472e970115e6b22a03e9",
  "entitlementType": "EXECUTABLE",
  "itemType": "DURABLE",
  "releaseInfo": [
    {
      "id": "490c112c4360471c9060e291ce8c6edd",
      "appId": "PepperQA",
      "compatibleApps": [],
      "platform": [
        "Windows"
      ],
      "dateAdded": "2019-10-18T16:16:57.972Z",
      "releaseNote": "",
      "versionTitle": ""
    }
  ],
  "developer": "Koch Media",
  "developerId": "o-jskfz28ywm2l56px6h9rlxplaysrtl",
  "eulaIds": [
    "egstore"
  ],
  "endOfSupport": false,
  "unsearchable": false
}