{
  "id": "92c9275b445245eb82f749ff9edf5eb1",
  "title": "Jay DLC1 Staging",
  "description": "Jay DLC1 Staging",
  "keyImages": [],
  "categories": [
    {
      "path": "public"
    },
    {
      "path": "games"
    },
    {
      "path": "applications"
    }
  ],
  "namespace": "752368fdba244e9386023cfb2b9d6ceb",
  "status": "ACTIVE",
  "creationDate": "2019-09-20T15:17:53.165Z",
  "lastModifiedDate": "2019-11-14T15:46:56.738Z",
  "customAttributes": {
    "CanRunOffline": {
      "type": "STRING",
      "value": "true"
    },
    "PresenceId": {
      "type": "STRING",
      "value": "752368fdba244e9386023cfb2b9d6ceb"
    },
    "MonitorPresence": {
      "type": "STRING",
      "value": "true"
    },
    "UseAccessControl": {
      "type": "STRING",
      "value": "false"
    },
    "RequirementsJson": {
      "type": "STRING",
      "value": "{}"
    },
    "CanSkipKoreanIdVerification": {
      "type": "STRING",
      "value": "true"
    },
    "FolderName": {
      "type": "STRING",
      "value": "JayDLC1Staging"
    }
  },
  "entitlementName": "92c9275b445245eb82f749ff9edf5eb1",
  "entitlementType": "EXECUTABLE",
  "itemType": "DURABLE",
  "releaseInfo": [
    {
      "id": "f1c7a60757ed4770904830da1607f3a4",
      "appId": "JayDLC1Staging",
      "platform": [
        "Windows"
      ],
      "dateAdded": "2019-09-10T00:00:00.000Z"
    }
  ],
  "developer": "Devolver Digital, Inc.",
  "developerId": "o-plnhdz2wfx5etjjeh88szjqy2gx8gw",
  "eulaIds": [
    "egstore"
  ],
  "endOfSupport": false,
  "unsearchable": false
}