{
  "id": "b23fab1e0f664923b48cb3b3970c5bab",
  "title": "Lobby",
  "description": "Lobby",
  "keyImages": [],
  "categories": [
    {
      "path": "public"
    },
    {
      "path": "games"
    },
    {
      "path": "applications"
    }
  ],
  "namespace": "e1055bf1e5654b93a27e19e6bb86cb2a",
  "status": "ACTIVE",
  "creationDate": "2020-05-08T16:39:06.681Z",
  "lastModifiedDate": "2020-05-08T16:57:13.501Z",
  "customAttributes": {
    "CanRunOffline": {
      "type": "STRING",
      "value": "true"
    },
    "FolderName": {
      "type": "STRING",
      "value": "Lobby"
    }
  },
  "entitlementName": "b23fab1e0f664923b48cb3b3970c5bab",
  "entitlementType": "EXECUTABLE",
  "itemType": "DURABLE",
  "releaseInfo": [
    {
      "id": "d754ca305143443b937807ed31ca99bd",
      "appId": "f62e82cdf45c404784747b3f0b1abdc5",
      "platform": [
        "Windows"
      ],
      "dateAdded": "2020-05-08T00:00:00.000Z"
    }
  ],
  "developer": "Kalypso Media",
  "developerId": "o-ntj9m7f2v76uksvjujurjfxtjkfawq",
  "eulaIds": [
    "egstore"
  ],
  "endOfSupport": false,
  "ageGatings": {},
  "unsearchable": false
}