{
  "id": "bec310471c4b488f8ab7950dd8719cf4",
  "title": "DevCakeAudience",
  "description": "DevCakeAudience",
  "categories": [
    {
      "path": "audience"
    },
    {
      "path": "developer"
    }
  ],
  "namespace": "0b9773fa2e964cf7bb5346925c162cb5",
  "status": "ACTIVE",
  "creationDate": "2020-07-20T18:18:44.063Z",
  "lastModifiedDate": "2020-08-27T11:49:34.151Z",
  "customAttributes": {
    "SupportedPlatforms": {
      "type": "STRING",
      "value": "Windows"
    }
  },
  "entitlementName": "bec310471c4b488f8ab7950dd8719cf4",
  "entitlementType": "AUDIENCE",
  "itemType": "DURABLE",
  "developer": "562 Interactive LLC",
  "developerId": "o-3fwjhd84kkymslexsxxhea2lrtsj68",
  "eulaIds": [
    "egstore"
  ],
  "endOfSupport": false,
  "requiresSecureAccount": false,
  "unsearchable": false
}