{
  "id": "c139af6a97284fafb8fcd1dbbe792ba0",
  "title": "LetheStaging",
  "description": "LetheStaging",
  "categories": [
    {
      "path": "public"
    },
    {
      "path": "games"
    },
    {
      "path": "applications"
    }
  ],
  "namespace": "df37f065c3f14eadbf011177396e2966",
  "status": "ACTIVE",
  "creationDate": "2020-10-26T16:28:13.685Z",
  "lastModifiedDate": "2020-11-16T20:03:52.768Z",
  "customAttributes": {
    "CanRunOffline": {
      "type": "STRING",
      "value": "true"
    },
    "FolderName": {
      "type": "STRING",
      "value": "LetheStaging"
    }
  },
  "entitlementName": "c139af6a97284fafb8fcd1dbbe792ba0",
  "entitlementType": "EXECUTABLE",
  "itemType": "DURABLE",
  "releaseInfo": [
    {
      "id": "5049253ba0064102a26299c52583a4b4",
      "appId": "7e2d3846905b4613a9741075f19d97d4",
      "platform": [
        "Windows"
      ],
      "dateAdded": "2020-11-16T20:03:50.532Z"
    }
  ],
  "developer": "SEGA of Europe",
  "developerId": "o-q3zwbk8kbbbgar9ql3x7d43rjj8bjl",
  "eulaIds": [
    "egstore"
  ],
  "endOfSupport": false,
  "ageGatings": {},
  "applicationId": "fghi4567WncMSw97kolM0Ff1UBPqwsE7",
  "requiresSecureAccount": false,
  "unsearchable": false
}