{
  "id": "ce25b8bd6b014f6ca99e15218606996f",
  "title": "CatnipStaging4DLC1",
  "description": "CatnipStaging4DLC1",
  "keyImages": [
    {
      "type": "DieselGameBox",
      "url": "https://cdn1.epicgames.com/catnip/item/Borderlands3_Promo-1440x810-6bcacdd8461e42e50e4038e0fb3260ee.jpg",
      "md5": "6bcacdd8461e42e50e4038e0fb3260ee",
      "width": 1440,
      "height": 810,
      "size": 295579,
      "uploadedDate": "2019-10-30T14:24:59.430Z"
    },
    {
      "type": "DieselGameBoxLogo",
      "url": "https://cdn1.epicgames.com/catnip/item/Borderlands3_Logo-720x209-8373e0df5612a9952fe79defb32e1322.png",
      "md5": "8373e0df5612a9952fe79defb32e1322",
      "width": 720,
      "height": 209,
      "size": 192732,
      "uploadedDate": "2019-10-30T14:25:16.085Z"
    }
  ],
  "categories": [
    {
      "path": "games"
    },
    {
      "path": "applications"
    }
  ],
  "namespace": "catnip",
  "status": "ACTIVE",
  "creationDate": "2020-02-28T20:36:14.066Z",
  "lastModifiedDate": "2020-06-15T20:52:55.766Z",
  "customAttributes": {
    "CanRunOffline": {
      "type": "STRING",
      "value": "true"
    },
    "OwnershipToken": {
      "type": "STRING",
      "value": "true"
    },
    "FolderName": {
      "type": "STRING",
      "value": "CatnipStaging4DLC1"
    }
  },
  "entitlementName": "ce25b8bd6b014f6ca99e15218606996f",
  "entitlementType": "EXECUTABLE",
  "itemType": "DURABLE",
  "releaseInfo": [
    {
      "id": "576f7fac22874385b23d203e598089cf",
      "appId": "d3285992126c4cdc95ddb9e19c923711",
      "compatibleApps": [],
      "platform": [
        "Windows"
      ],
      "dateAdded": "2019-08-20T00:00:00.000Z",
      "releaseNote": "",
      "versionTitle": ""
    }
  ],
  "developer": "2K Games, Inc.",
  "developerId": "o-37m6jbj5wcvrcvm4wusv7nazdfvbjk",
  "eulaIds": [
    "egstore"
  ],
  "endOfSupport": false,
  "unsearchable": false
}