{
  "id": "dd94a695b16a4ab39fa718e1b1f3b57a",
  "title": "Pewee Consumable",
  "description": "Pewee Consumable",
  "keyImages": [],
  "categories": [
    {
      "path": "audience"
    },
    {
      "path": "public"
    }
  ],
  "namespace": "933ada2ec45e4184ae840d64c99e0ba9",
  "status": "ACTIVE",
  "creationDate": "2019-12-12T22:36:36.909Z",
  "lastModifiedDate": "2020-12-04T16:20:25.897Z",
  "customAttributes": {
    "SupportedPlatforms": {
      "type": "STRING",
      "value": "Windows"
    }
  },
  "entitlementName": "dd94a695b16a4ab39fa718e1b1f3b57a",
  "entitlementType": "AUDIENCE",
  "itemType": "CONSUMABLE",
  "developer": "Hi-Rez Studios",
  "developerId": "o-7aklpapnk74p66sqs6hm5byt29wp66",
  "useCount": 1,
  "eulaIds": [
    "egstore"
  ],
  "endOfSupport": false,
  "unsearchable": false
}