{
  "id": "e4c406ce4e054e6691734ec263e0c6d9",
  "title": "The Sojourn General Audience",
  "description": "The Sojourn General Audience",
  "keyImages": [],
  "categories": [
    {
      "path": "audience"
    },
    {
      "path": "public"
    }
  ],
  "namespace": "ada169f07b81464a9fc06a7d6896101d",
  "status": "ACTIVE",
  "creationDate": "2019-06-02T04:20:42.473Z",
  "lastModifiedDate": "2019-10-18T16:18:51.428Z",
  "customAttributes": {
    "SupportedPlatforms": {
      "type": "STRING",
      "value": "Windows"
    }
  },
  "entitlementName": "e4c406ce4e054e6691734ec263e0c6d9",
  "entitlementType": "AUDIENCE",
  "itemType": "DURABLE",
  "developer": "Iceberg Interactive",
  "developerId": "o-ftmts7pjfvdywkby885rdzl4hdbtys",
  "eulaIds": [
    "egstore"
  ],
  "endOfSupport": false,
  "selfRefundable": true,
  "unsearchable": false
}